componentize_py-0.19.2.dist-info/METADATA
componentize_py-0.19.2.dist-info/WHEEL
componentize_py-0.19.2.dist-info/entry_points.txt
componentize_py-0.19.2.dist-info/licenses/LICENSE
componentize_py/__init__.py
componentize_py/componentize_py.pyd
componentize_py-0.19.2.dist-info/RECORD
