Metadata-Version: 2.4
Name: componentize-py
Version: 0.19.2
License-File: LICENSE
Summary: Tool to package Python applications as WebAssembly components
Keywords: webassembly,wasm,component
Author-email: Fermyon Engineering <engineering@fermyon.com>
Maintainer-email: Fermyon Engineering <engineering@fermyon.com>
Project-URL: repository, https://github.com/bytecodealliance/componentize-py
